{"is_source_file": false, "format": "", "description": "", "external_files": [], "external_methods": [], "published": [], "classes": [], "methods": [], "calls": [], "search-terms": [], "state": 2, "file_id": 5, "knowledge_revision": 8, "git_revision": "aa4f48a7d61841e03c861a0a76cf578ba69c120c", "hash": "b584d8936b91a01f13a45c2252449033", "format-version": 4, "code-base-name": "bug_detector_backend", "filename": "bug_detector_backend/Properties/launchSettings.json", "revision_history": [{"8": "aa4f48a7d61841e03c861a0a76cf578ba69c120c"}]}